[{"target_score": 0.85, "percentile": 0.01, "accuracy": 0.948, "average_token_count": 19435.528}, {"target_score": 0.85, "percentile": 0.02, "accuracy": 0.948, "average_token_count": 19134.06}, {"target_score": 0.85, "percentile": 0.035, "accuracy": 0.948, "average_token_count": 18923.712}, {"target_score": 0.85, "percentile": 0.05, "accuracy": 0.948, "average_token_count": 18710.256}, {"target_score": 0.85, "percentile": 0.075, "accuracy": 0.948, "average_token_count": 18467.134}, {"target_score": 0.85, "percentile": 0.1, "accuracy": 0.948, "average_token_count": 18236.326}, {"target_score": 0.9, "percentile": 0.01, "accuracy": 0.948, "average_token_count": 20459.464}, {"target_score": 0.9, "percentile": 0.02, "accuracy": 0.948, "average_token_count": 20266.208}, {"target_score": 0.9, "percentile": 0.035, "accuracy": 0.948, "average_token_count": 20065.398}, {"target_score": 0.9, "percentile": 0.05, "accuracy": 0.948, "average_token_count": 19936.616}, {"target_score": 0.9, "percentile": 0.075, "accuracy": 0.948, "average_token_count": 19723.932}, {"target_score": 0.9, "percentile": 0.1, "accuracy": 0.948, "average_token_count": 19486.092}, {"target_score": 0.925, "percentile": 0.01, "accuracy": 0.948, "average_token_count": 20894.034}, {"target_score": 0.925, "percentile": 0.02, "accuracy": 0.948, "average_token_count": 20782.808}, {"target_score": 0.925, "percentile": 0.035, "accuracy": 0.948, "average_token_count": 20686.604}, {"target_score": 0.925, "percentile": 0.05, "accuracy": 0.948, "average_token_count": 20568.978}, {"target_score": 0.925, "percentile": 0.075, "accuracy": 0.948, "average_token_count": 20445.506}, {"target_score": 0.925, "percentile": 0.1, "accuracy": 0.948, "average_token_count": 20349.454}, {"target_score": 0.95, "percentile": 0.01, "accuracy": 0.948, "average_token_count": 21381.112}, {"target_score": 0.95, "percentile": 0.02, "accuracy": 0.948, "average_token_count": 21313.956}, {"target_score": 0.95, "percentile": 0.035, "accuracy": 0.948, "average_token_count": 21227.978}, {"target_score": 0.95, "percentile": 0.05, "accuracy": 0.948, "average_token_count": 21189.468}, {"target_score": 0.95, "percentile": 0.075, "accuracy": 0.948, "average_token_count": 21110.662}, {"target_score": 0.95, "percentile": 0.1, "accuracy": 0.948, "average_token_count": 21035.126}, {"target_score": 0.96, "percentile": 0.01, "accuracy": 0.948, "average_token_count": 21698.078}, {"target_score": 0.96, "percentile": 0.02, "accuracy": 0.948, "average_token_count": 21626.172}, {"target_score": 0.96, "percentile": 0.035, "accuracy": 0.948, "average_token_count": 21527.966}, {"target_score": 0.96, "percentile": 0.05, "accuracy": 0.948, "average_token_count": 21430.398}, {"target_score": 0.96, "percentile": 0.075, "accuracy": 0.948, "average_token_count": 21367.748}, {"target_score": 0.96, "percentile": 0.1, "accuracy": 0.948, "average_token_count": 21318.884}, {"target_score": 0.97, "percentile": 0.01, "accuracy": 0.948, "average_token_count": 21848.606}, {"target_score": 0.97, "percentile": 0.02, "accuracy": 0.948, "average_token_count": 21818.834}, {"target_score": 0.97, "percentile": 0.035, "accuracy": 0.948, "average_token_count": 21771.592}, {"target_score": 0.97, "percentile": 0.05, "accuracy": 0.948, "average_token_count": 21735.026}, {"target_score": 0.97, "percentile": 0.075, "accuracy": 0.948, "average_token_count": 21692.344}, {"target_score": 0.97, "percentile": 0.1, "accuracy": 0.948, "average_token_count": 21649.546}, {"target_score": 0.98, "percentile": 0.01, "accuracy": 0.948, "average_token_count": 22015.158}, {"target_score": 0.98, "percentile": 0.02, "accuracy": 0.948, "average_token_count": 21974.75}, {"target_score": 0.98, "percentile": 0.035, "accuracy": 0.948, "average_token_count": 21936.142}, {"target_score": 0.98, "percentile": 0.05, "accuracy": 0.948, "average_token_count": 21907.534}, {"target_score": 0.98, "percentile": 0.075, "accuracy": 0.948, "average_token_count": 21883.048}, {"target_score": 0.98, "percentile": 0.1, "accuracy": 0.948, "average_token_count": 21843.802}, {"target_score": 0.99, "percentile": 0.01, "accuracy": 0.948, "average_token_count": 22103.786}, {"target_score": 0.99, "percentile": 0.02, "accuracy": 0.948, "average_token_count": 22102.962}, {"target_score": 0.99, "percentile": 0.035, "accuracy": 0.948, "average_token_count": 22097.406}, {"target_score": 0.99, "percentile": 0.05, "accuracy": 0.948, "average_token_count": 22097.406}, {"target_score": 0.99, "percentile": 0.075, "accuracy": 0.948, "average_token_count": 22062.21}, {"target_score": 0.99, "percentile": 0.1, "accuracy": 0.948, "average_token_count": 22052.902}]